README.md
setup.py
pulumi_whisparr/__init__.py
pulumi_whisparr/_utilities.py
pulumi_whisparr/provider.py
pulumi_whisparr/pulumi-plugin.json
pulumi_whisparr/py.typed
pulumi_whisparr.egg-info/PKG-INFO
pulumi_whisparr.egg-info/SOURCES.txt
pulumi_whisparr.egg-info/dependency_links.txt
pulumi_whisparr.egg-info/not-zip-safe
pulumi_whisparr.egg-info/requires.txt
pulumi_whisparr.egg-info/top_level.txt
pulumi_whisparr/config/__init__.py
pulumi_whisparr/config/vars.py
pulumi_whisparr/downloadclients/__init__.py
pulumi_whisparr/downloadclients/aria2.py
pulumi_whisparr/downloadclients/config.py
pulumi_whisparr/downloadclients/deluge.py
pulumi_whisparr/downloadclients/download_client.py
pulumi_whisparr/downloadclients/flood.py
pulumi_whisparr/downloadclients/get_config.py
pulumi_whisparr/downloadclients/get_download_client.py
pulumi_whisparr/downloadclients/get_download_clients.py
pulumi_whisparr/downloadclients/get_remote_path_mapping.py
pulumi_whisparr/downloadclients/get_remote_path_mappings.py
pulumi_whisparr/downloadclients/hadouken.py
pulumi_whisparr/downloadclients/nzbget.py
pulumi_whisparr/downloadclients/nzbvortex.py
pulumi_whisparr/downloadclients/outputs.py
pulumi_whisparr/downloadclients/pneumatic.py
pulumi_whisparr/downloadclients/qbittorrent.py
pulumi_whisparr/downloadclients/remote_path_mapping.py
pulumi_whisparr/downloadclients/rtorrent.py
pulumi_whisparr/downloadclients/sabnzbd.py
pulumi_whisparr/downloadclients/torrent_blackhole.py
pulumi_whisparr/downloadclients/torrent_download_station.py
pulumi_whisparr/downloadclients/transmission.py
pulumi_whisparr/downloadclients/usenet_blackhole.py
pulumi_whisparr/downloadclients/usenet_download_station.py
pulumi_whisparr/downloadclients/utorrent.py
pulumi_whisparr/downloadclients/vuze.py
pulumi_whisparr/importlists/__init__.py
pulumi_whisparr/importlists/config.py
pulumi_whisparr/importlists/couch_potato.py
pulumi_whisparr/importlists/custom.py
pulumi_whisparr/importlists/exclusion.py
pulumi_whisparr/importlists/get_config.py
pulumi_whisparr/importlists/get_exclusion.py
pulumi_whisparr/importlists/get_exclusions.py
pulumi_whisparr/importlists/get_import_list.py
pulumi_whisparr/importlists/get_import_lists.py
pulumi_whisparr/importlists/imdb.py
