Metadata-Version: 2.1
Name: pulumi-whisparr
Version: 2.0.0a2
Summary: A Pulumi package for creating and managing Whisparr resources
Home-page: https://github.com/MaienM/pulumi-whisparr
License: Apache-2.0
Project-URL: Repository, https://github.com/MaienM/pulumi-whisparr
Keywords: pulumi whisparr category/utility
Requires-Python: >=3.7
